mlocks/__init__.py
mlocks/example.py
mlocks-0.0.1.dist-info/LICENSE
mlocks-0.0.1.dist-info/METADATA
mlocks-0.0.1.dist-info/WHEEL
mlocks-0.0.1.dist-info/top_level.txt
mlocks-0.0.1.dist-info/RECORD
